FoliumZhongwenWendang/README.md
FoliumZhongwenWendang/__init__.py
FoliumZhongwenWendang/__main__.py
FoliumZhongwenWendang/file.epub
FoliumZhongwenWendang/index.html
FoliumZhongwenWendang/css/__init__.py
FoliumZhongwenWendang/css/annotations.css
FoliumZhongwenWendang/css/main.css
FoliumZhongwenWendang/css/normalize.css
FoliumZhongwenWendang/css/popup.css
FoliumZhongwenWendang/font/__init__.py
FoliumZhongwenWendang/font/fontello.eot
FoliumZhongwenWendang/font/fontello.svg
FoliumZhongwenWendang/font/fontello.ttf
FoliumZhongwenWendang/font/fontello.woff
FoliumZhongwenWendang/img/__init__.py
FoliumZhongwenWendang/img/annotator-glyph-sprite.png
FoliumZhongwenWendang/img/annotator-icon-sprite.png
FoliumZhongwenWendang/img/apple-touch-icon.png
FoliumZhongwenWendang/img/cancelfullscreen.png
FoliumZhongwenWendang/img/close.png
FoliumZhongwenWendang/img/fullscreen.png
FoliumZhongwenWendang/img/loader.gif
FoliumZhongwenWendang/img/menu-icon.png
FoliumZhongwenWendang/img/save.png
FoliumZhongwenWendang/img/saved.png
FoliumZhongwenWendang/img/settings-s.png
FoliumZhongwenWendang/img/settings.png
FoliumZhongwenWendang/img/star.png
FoliumZhongwenWendang/js/__init__.py
FoliumZhongwenWendang/js/epub.js
FoliumZhongwenWendang/js/epub.min.js
FoliumZhongwenWendang/js/epub.min.map
FoliumZhongwenWendang/js/hooks.min.js
FoliumZhongwenWendang/js/hooks.min.map
FoliumZhongwenWendang/js/reader.js
FoliumZhongwenWendang/js/reader.js.map
FoliumZhongwenWendang/js/reader.min.js
FoliumZhongwenWendang/js/reader.min.map
FoliumZhongwenWendang/js/hooks/__init__.py
FoliumZhongwenWendang/js/hooks/extensions/__init__.py
FoliumZhongwenWendang/js/hooks/extensions/highlight.js
FoliumZhongwenWendang/js/libs/__init__.py
FoliumZhongwenWendang/js/libs/jquery.min.js
FoliumZhongwenWendang/js/libs/localforage.min.js
FoliumZhongwenWendang/js/libs/screenfull.js
FoliumZhongwenWendang/js/libs/screenfull.min.js
FoliumZhongwenWendang/js/libs/zip.min.js
FoliumZhongwenWendang/js/plugins/__init__.py
folium_zhongwen_wendang-2024.3.5.0.dist-info/METADATA
folium_zhongwen_wendang-2024.3.5.0.dist-info/WHEEL
folium_zhongwen_wendang-2024.3.5.0.dist-info/entry_points.txt
folium_zhongwen_wendang-2024.3.5.0.dist-info/top_level.txt
folium_zhongwen_wendang-2024.3.5.0.dist-info/RECORD
